odoo/addons/account_spread_cost_revenue/README.rst
odoo/addons/account_spread_cost_revenue/__init__.py
odoo/addons/account_spread_cost_revenue/__manifest__.py
odoo/addons/account_spread_cost_revenue/data/spread_cron.xml
odoo/addons/account_spread_cost_revenue/i18n/account_spread_cost_revenue.pot
odoo/addons/account_spread_cost_revenue/i18n/es.po
odoo/addons/account_spread_cost_revenue/i18n/fr.po
odoo/addons/account_spread_cost_revenue/i18n/it.po
odoo/addons/account_spread_cost_revenue/i18n/nl.po
odoo/addons/account_spread_cost_revenue/i18n/pt.po
odoo/addons/account_spread_cost_revenue/models/__init__.py
odoo/addons/account_spread_cost_revenue/models/account_move.py
odoo/addons/account_spread_cost_revenue/models/account_move_line.py
odoo/addons/account_spread_cost_revenue/models/account_spread.py
odoo/addons/account_spread_cost_revenue/models/account_spread_line.py
odoo/addons/account_spread_cost_revenue/models/account_spread_template.py
odoo/addons/account_spread_cost_revenue/models/res_company.py
odoo/addons/account_spread_cost_revenue/readme/CONFIGURE.md
odoo/addons/account_spread_cost_revenue/readme/CONTRIBUTORS.md
odoo/addons/account_spread_cost_revenue/readme/CREDITS.md
odoo/addons/account_spread_cost_revenue/readme/DESCRIPTION.md
odoo/addons/account_spread_cost_revenue/readme/HISTORY.md
odoo/addons/account_spread_cost_revenue/readme/USAGE.md
odoo/addons/account_spread_cost_revenue/security/account_spread_security.xml
odoo/addons/account_spread_cost_revenue/security/ir.model.access.csv
odoo/addons/account_spread_cost_revenue/static/description/create_spread.png
odoo/addons/account_spread_cost_revenue/static/description/icon.png
odoo/addons/account_spread_cost_revenue/static/description/index.html
odoo/addons/account_spread_cost_revenue/static/description/invoice_line_1.png
odoo/addons/account_spread_cost_revenue/static/description/invoice_line_2.png
odoo/addons/account_spread_cost_revenue/static/description/spread.png
odoo_addon_account_spread_cost_revenue-18.0.1.0.0.2.dist-info/METADATA
odoo_addon_account_spread_cost_revenue-18.0.1.0.0.2.dist-info/WHEEL
odoo_addon_account_spread_cost_revenue-18.0.1.0.0.2.dist-info/top_level.txt
odoo_addon_account_spread_cost_revenue-18.0.1.0.0.2.dist-info/RECORD
