Metadata-Version: 2.1
Name: odoo-addon-account_spread_cost_revenue
Version: 18.0.1.0.0.2
Requires-Python: >=3.10
Requires-Dist: odoo==18.0.*
Summary: Spread costs and revenues over a custom period
Home-page: https://github.com/OCA/account-financial-tools
License: AGPL-3
Author: Onestein,Odoo Community Association (OCA)
Author-email: support@odoo-community.org
Classifier: Programming Language :: Python
Classifier: Framework :: Odoo
Classifier: Framework :: Odoo :: 18.0
Classifier: License :: OSI Approved :: GNU Affero General Public License v3
Classifier: Development Status :: 4 - Beta
